{
  "login": "deborafranqueta",
  "id": 72817900,
  "node_id": "MDQ6VXNlcjcyODE3OTAw",
  "avatar_url": "https://avatars.githubusercontent.com/u/72817900?v=4",
  "gravatar_id": "",
  "url": "https://api.github.com/users/deborafranqueta",
  "html_url": "https://github.com/deborafranqueta",
  "followers_url": "https://api.github.com/users/deborafranqueta/followers",
  "following_url": "https://api.github.com/users/deborafranqueta/following{/other_user}",
  "gists_url": "https://api.github.com/users/deborafranqueta/gists{/gist_id}",
  "starred_url": "https://api.github.com/users/deborafranqueta/starred{/owner}{/repo}",
  "subscriptions_url": "https://api.github.com/users/deborafranqueta/subscriptions",
  "organizations_url": "https://api.github.com/users/deborafranqueta/orgs",
  "repos_url": "https://api.github.com/users/deborafranqueta/repos",
  "events_url": "https://api.github.com/users/deborafranqueta/events{/privacy}",
  "received_events_url": "https://api.github.com/users/deborafranqueta/received_events",
  "type": "User",
  "site_admin": false,
  "name": "Débora Franquêta",
  "company": "Graduanda em ADS I Uninassau",
  "blog": "https://portfolio-pi-blush.vercel.app/",
  "location": "Aracaju- SE",
  "email": null,
  "hireable": null,
  "bio": "💻 Desenvolvedora Full Stack em Formação        \r\n                   📍 Aracaju-Se",
  "twitter_username": "dfranqueta",
  "public_repos": 11,
  "public_gists": 0,
  "followers": 8,
  "following": 29,
  "created_at": "2020-10-13T17:18:45Z",
  "updated_at": "2021-10-22T21:35:23Z"
}